oracles_client/__init__.py
oracles_client/check.py
oracles_client/utils.py
p1_oracles_client-0.1.0.dev0.dist-info/METADATA
p1_oracles_client-0.1.0.dev0.dist-info/WHEEL
p1_oracles_client-0.1.0.dev0.dist-info/entry_points.txt
p1_oracles_client-0.1.0.dev0.dist-info/top_level.txt
p1_oracles_client-0.1.0.dev0.dist-info/RECORD
